lumiere_pytorch/__init__.py
lumiere_pytorch/lumiere.py
lumiere_pytorch/mp_lumiere.py
lumiere_pytorch-0.0.24.dist-info/LICENSE
lumiere_pytorch-0.0.24.dist-info/METADATA
lumiere_pytorch-0.0.24.dist-info/WHEEL
lumiere_pytorch-0.0.24.dist-info/top_level.txt
lumiere_pytorch-0.0.24.dist-info/RECORD
