Metadata-Version: 2.1
Name: lumiere-pytorch
Version: 0.0.24
Summary: Lumiere
Home-page: https://github.com/lucidrains/lumiere-pytorch
Author: Phil Wang
Author-email: lucidrains@gmail.com
License: MIT
Keywords: artificial intelligence,deep learning,text-to-video
Classifier: Development Status :: 4 - Beta
Classifier: Intended Audience :: Developers
Classifier: Topic :: Scientific/Engineering :: Artificial Intelligence
Classifier: License :: OSI Approved :: MIT License
Classifier: Programming Language :: Python :: 3.6
License-File: LICENSE
Requires-Dist: beartype
Requires-Dist: einops >=0.7.0
Requires-Dist: optree
Requires-Dist: torch >=2.0
Requires-Dist: x-transformers
